<?xml version="1.0" encoding="UTF-8" ?>
<!DOCTYPE generatorConfiguration PUBLIC "-//mybatis.org//DTD MyBatis Generator Configuration 1.0//EN"
        "http://mybatis.org/dtd/mybatis-generator-config_1_0.dtd" >
<generatorConfiguration>
    <!--加载属性文件 -->
    <properties resource="jdbc.properties"/>

    <context id="context" targetRuntime="MyBatis3">

        <!-- 生成的Java文件的编码-->
        <property name="javaFileEncoding" value="UTF-8"/>
        <!-- 格式化java代码-->
        <property name="javaFormatter" value="org.mybatis.generator.api.dom.DefaultJavaFormatter"/>
        <!-- 格式化XML代码-->
        <property name="xmlFormatter" value="org.mybatis.generator.api.dom.DefaultXmlFormatter"/>

        <!-- 实现自定义的代码生成器插件 -->
        <plugin type="caojx.learn.plugin.VoPlugin">
            <property name="targetProject" value="src/test/java"/>
            <property name="targetPackage" value="com.lianjia.cto.ke.vo"/>
            <property name="daoSuperClass" value="caojx.learn.util.KeMapper"/>
            <!--Vo扩展名-->
            <property name="voSuffix" value="Vo"/>
            <!--author-->
            <property name="author" value="caojianxinag001"/>
        </plugin>

        <!--自定义注释插件-->
        <commentGenerator type="caojx.learn.comment.MyCommentGeneratorForVo">
            <property name="suppressAllComments" value="false"></property>
            <!--author-->
            <property name="author" value="caojianxinag001"/>
        </commentGenerator>

        <!-- 数据库连接URL，用户名，密码 -->
        <jdbcConnection driverClass="${jdbc.driver}" connectionURL="${jdbc.url}" userId="${jdbc.username}"
                        password="${jdbc.password}">
        </jdbcConnection>

        <!--生成模型的包名和位置
            targetPackage     指定生成的model生成所在的包名
            targetProject     指定在该项目下所在的路径
        -->
        <javaModelGenerator targetPackage="com.lianjia.cto.ke.vo" targetProject="src/test/java/">
            <property name="rootClass" value="caojx.learn.pojo.BaseVo"/>
        </javaModelGenerator>

        <!--生成哪些表对应的Vo -->
        <table tableName="%" enableSelectByExample="false" enableDeleteByExample="false"
               enableCountByExample="false" enableUpdateByExample="false"
               selectByExampleQueryId="false">
            <columnOverride column="city_name" property="cityName"/>
        </table>

         <!--指定数据库表-->
<!--        <table  tableName="mov_account_log" enableSelectByExample="false" enableDeleteByExample="false"
                enableCountByExample="false" enableUpdateByExample="false"
                selectByExampleQueryId="false">
        </table>-->
    </context>
</generatorConfiguration>